Workbook

Sheet RESUMEN
J3: 1 | L3: al día
J4: 2 | L4: a 15 días
J5: 3 | L5: a 30 días
J6: 4 | L6: a 45 días
J7: 5 | L7: a 60 días
J8: 6 | L8: a 90 días
B9: Obra: | C9: REMODELACION BAÑOS SHC LA CALERA
B10: Dirección: | C10: MALL OPEN PLAZA LA CALERA
B12: PLANILLA DE ESTADOS DE PAGO DE SUBCONTRATOS
B14: Comienzo de Obra: | C14: 45875 | D14: Días de Obra: | E14: =I17-C14 -> 72 | I14: ADICIONALES
B15: Cierre de Obra: | C15: 45935 | D15: Días de Obra | E15: =C15-C14 -> 60 | I15: EEPP#03
I16: PRSENTE | J16: Observación | L16: ACUMULADO | N16: ANTERIORES | P16: Saldo y/o Retención | R16: Avance Financiero | T16: Retención
A17: Nº | B17: SUBCONTRATISTA | C17: RUT | D17: CONCEPTO | E17: CONTRATO | F17: FACTURA | G17: F.pago | H17: Fecha de Pago Oficina | I17: 45947 | R17: % | T17: 0.05
A19: 1 | B19: FENOLICO EXPRESS | C19: 78007082-K | D19: DIVISIONES FENOLICAS | E19: ='1'!G43 -> 65000 | F19: CONTRATISTA | I19: ='1'!M43 -> 0 | L19: =+'1'!I43 -> 65000 | N19: ='1'!K43 -> 65000 | P19: =E19-L19 -> 0 | R19: =L19/E19 -> 1 | T19: no
A20: 2 | B20: JONATHAN PARDO | C20: 18.512.369-3 | D20: GASFITER | E20: ='2'!G44 -> 1900000 | F20: CONTRATISTA | G20: 2 | H20: 2 | I20: ='2'!M44 -> 450000 | J20: AD 10 EN EJECUCIÓN | L20: =+'2'!I44 -> 1900000 | N20: ='2'!K44 -> 1450000 | P20: =E20-L20 -> 0 | R20: =L20/E20 -> 1 | T20: no
A21: 3 | B21: WOGE | C21: 77.573.776-K | D21: CUBREJUNTA | E21: ='3'!G46 -> 34680 | F21: CONTRATISTA | I21: ='3'!M46 -> 0 | L21: =+'3'!I46 -> 34680 | N21: ='3'!K46 -> 34680 | P21: =E21-L21 -> 0 | R21: =L21/E21 -> 1
B22: TOTAL SUBCONTRATOS | E22: =SUM(E18:E21) -> 1999680 | I22: =SUM(I18:I21) -> 450000 | L22: =SUM(L18:L21) -> 1999680 | M22: =SUM(M18:M21) -> 0 | N22: =SUM(N18:N21) -> 1549680 | P22: =SUM(P18:P21) -> 0 | R22: =L22/E22 -> 1
D24: IVA | E24: =E22*0.19 -> 379939.2 | G24: IVA | I24: =+I22*0.19 -> 85500
E25: =SUM(E22:E24) -> 2379619.2 | I25: =SUM(I22:I24) -> 535500
L30: Vº Bº ADMINISTRADOR OBRA

Sheet 1
B3: ESTADO DE PAGO Nº 1
M5: =+RESUMEN!#REF! -> #REF!
B6: OBRA | C6: =+RESUMEN!C9 -> REMODELACION BAÑOS SHC LA CALERA
B7: UBICACIÓN | C7: =+RESUMEN!C10 -> MALL OPEN PLAZA LA CALERA | M7: Estado de pago
B8: CONTRATISTA | C8: =+RESUMEN!B19 -> FENOLICO EXPRESS | M8: =+RESUMEN!I15 -> EEPP#03
B9: DIRECCION
B10: R.U.T. | C10: =+RESUMEN!C19 -> 78007082-K
B11: OC
B13: Monto Contratado a la Fecha | E13: =G40 -> 65000 | L13: FECHA | M13: =+RESUMEN!I17 -> 45947
G15: TOTAL | H15: Avance Acumulado | J15: Avance E.P. ANTERIOR | L15: Presente
B16: ITEM | C16: DETALLE PARTIDAS | G16: CONTRATO | H16: a la Fecha | L16: Estado de Pago
H17: % | I17: Monto $ | J17: % | K17: Monto $ | L17: % | M17: Monto $
C18: ADICIONAL | D18: UN | E18: CANT | F18: PU
B19: 1 | C19: AD 04 ESCUADRA ACERO INOX | D19: UNI | E19: 52 | F19: 1250 | G19: =+F19*E19 -> 65000 | H19: 1 | I19: =H19*G19 -> 65000 | J19: 1 | K19: =J19*G19 -> 65000 | L19: =H19-J19 -> 0 | M19: =L19*G19 -> 0
C40: SUB TOTAL | G40: =SUM(G18:G39) -> 65000 | I40: =SUM(I18:I39) -> 65000 | K40: =SUM(K18:K39) -> 65000 | M40: =SUM(M18:M39) -> 0
C41: Retención | I41: =I40*F41 -> 0 | K41: =K40*F41 -> 0 | M41: =M40*F41 -> 0
C42: PAGO RETENCIONES | G42: 0 | H42: 0 | I42: =H42*G42 -> 0 | J42: 0 | K42: =G42*J42 -> 0 | L42: =H42-J42 -> 0 | M42: =L42*G42 -> 0
C43: NETO | G43: =G40-G41+G42 -> 65000 | H43: ru | I43: =+I40-I41 -> 65000 | K43: =+K40-K41 -> 65000 | M43: =+M40-M41 -> 0
C44: 19% VALOR IVA | G44: =G43*19% -> 12350 | I44: =I43*19% -> 12350 | K44: =K43*19% -> 12350 | M44: =+M43*0.19 -> 0
C45: TOTAL | G45: =SUM(G43:G44) -> 77350 | I45: =SUM(I43:I44) -> 77350 | K45: =SUM(K43:K44) -> 77350 | M45: =SUM(M43:M44) -> 0
H53: Constructora MM

Sheet 2
B3: ESTADO DE PAGO Nº 1
M5: =+RESUMEN!#REF! -> #REF!
B6: OBRA | C6: =+RESUMEN!C9 -> REMODELACION BAÑOS SHC LA CALERA
B7: UBICACIÓN | C7: =+RESUMEN!C10 -> MALL OPEN PLAZA LA CALERA | M7: Estado de pago
B8: CONTRATISTA | C8: =+RESUMEN!B20 -> JONATHAN PARDO | M8: =+RESUMEN!I15 -> EEPP#03
B9: DIRECCION
B10: R.U.T. | C10: =+RESUMEN!C20 -> 18.512.369-3
B11: OC
B13: Monto Contratado a la Fecha | E13: =G41 -> 1900000 | L13: FECHA | M13: =+RESUMEN!I17 -> 45947
G15: TOTAL | H15: Avance Acumulado | J15: Avance E.P. ANTERIOR | L15: Presente
B16: ITEM | C16: DETALLE PARTIDAS | G16: CONTRATO | H16: a la Fecha | L16: Estado de Pago
H17: % | I17: Monto $ | J17: % | K17: Monto $ | L17: % | M17: Monto $
C18: ADICIONALES 03 | D18: UN | E18: CANT | F18: PU
B19: 1 | C19: AD 03 CAMBIO DE LLAVE DE PASO WC: INCLUYE MATERIALES | D19: UNI | E19: 3 | F19: 230000 | G19: =+F19*E19 -> 690000 | H19: 1 | I19: =H19*G19 -> 690000 | J19: 1 | K19: =J19*G19 -> 690000 | L19: =H19-J19 -> 0 | M19: =L19*G19 -> 0
C21: ADICIONALES 06
C22: Instalación llave paso de 3/4 sectorizacion lava manos A/F | D22: UNI | E22: 2 | F22: 110000 | G22: =+F22*E22 -> 220000 | H22: 1 | I22: =H22*G22 -> 220000 | J22: 1 | K22: =J22*G22 -> 220000 | L22: =H22-J22 -> 0 | M22: =L22*G22 -> 0
C23: Instalación llave paso de 1" sectorizacion Duchas A/F | D23: UNI | E23: 2 | F23: 110000 | G23: =+F23*E23 -> 220000 | H23: 1 | I23: =H23*G23 -> 220000 | J23: 1 | K23: =J23*G23 -> 220000 | L23: =H23-J23 -> 0 | M23: =L23*G23 -> 0
C25: ADICIONALES 08
C26: Instalacion de termo adicional | D26: UNI | E26: 1 | F26: 200000 | G26: =+F26*E26 -> 200000 | H26: 1 | I26: =H26*G26 -> 200000 | J26: 1 | K26: =J26*G26 -> 200000 | L26: =H26-J26 -> 0 | M26: =L26*G26 -> 0
C27: Eliminacion de puntos de duchas existentes | D27: UNI | E27: 6 | F27: 15000 | G27: =+F27*E27 -> 90000 | H27: 1 | I27: =H27*G27 -> 90000 | J27: 1 | K27: =J27*G27 -> 90000 | L27: =H27-J27 -> 0 | M27: =L27*G27 -> 0
C28: eliminacion de puntos de lavamanos existentes | D28: UNI | E28: 2 | F28: 15000 | G28: =+F28*E28 -> 30000 | H28: 1 | I28: =H28*G28 -> 30000 | J28: 1 | K28: =J28*G28 -> 30000 | L28: =H28-J28 -> 0 | M28: =L28*G28 -> 0
C30: ADICIONAL 10
C31: FIJACIONES EN CAÑERIAS DE AGUA | D31: GL | E31: 1 | F31: 450000 | G31: =+F31*E31 -> 450000 | H31: 1 | I31: =H31*G31 -> 450000 | J31: 0 | K31: =J31*G31 -> 0 | L31: =H31-J31 -> 1 | M31: =L31*G31 -> 450000
C41: SUB TOTAL | G41: =SUM(G18:G40) -> 1900000 | I41: =SUM(I18:I40) -> 1900000 | K41: =SUM(K18:K40) -> 1450000 | M41: =SUM(M18:M40) -> 450000
C42: Retención | I42: =I41*F42 -> 0 | K42: =K41*F42 -> 0 | M42: =M41*F42 -> 0
C43: PAGO RETENCIONES | G43: 0 | H43: 0 | I43: =H43*G43 -> 0 | J43: 0 | K43: =G43*J43 -> 0 | L43: =H43-J43 -> 0 | M43: =L43*G43 -> 0
C44: NETO | G44: =G41-G42+G43 -> 1900000 | H44: ru | I44: =+I41-I42 -> 1900000 | K44: =+K41-K42 -> 1450000 | M44: =+M41-M42 -> 450000
C45: 19% VALOR IVA | G45: =G44*19% -> 361000 | I45: =I44*19% -> 361000 | K45: =K44*19% -> 275500 | M45: =+M44*0.19 -> 85500
C46: TOTAL | G46: =SUM(G44:G45) -> 2261000 | I46: =SUM(I44:I45) -> 2261000 | K46: =SUM(K44:K45) -> 1725500 | M46: =SUM(M44:M45) -> 535500
H54: Constructora MM

Sheet 3
B3: ESTADO DE PAGO Nº 1
M5: =+RESUMEN!#REF! -> #REF!
B6: OBRA | C6: =+RESUMEN!C9 -> REMODELACION BAÑOS SHC LA CALERA
B7: UBICACIÓN | C7: =+RESUMEN!C10 -> MALL OPEN PLAZA LA CALERA | M7: Estado de pago
B8: CONTRATISTA | C8: =+RESUMEN!#REF! -> #REF! | M8: =+RESUMEN!I15 -> EEPP#03
B9: DIRECCION
B10: R.U.T. | C10: =+RESUMEN!#REF! -> #REF!
B11: OC
B13: Monto Contratado a la Fecha | E13: =G43 -> 34680 | L13: FECHA | M13: =+RESUMEN!I17 -> 45947
G15: TOTAL | H15: Avance Acumulado | J15: Avance E.P. ANTERIOR | L15: Presente
B16: ITEM | C16: DETALLE PARTIDAS | G16: CONTRATO | H16: a la Fecha | L16: Estado de Pago
H17: % | I17: Monto $ | J17: % | K17: Monto $ | L17: % | M17: Monto $
C18: ADICIONAL 04 | D18: UN | E18: CANT | F18: PU
B19: 1 | C19: CUBREJUNTA ACERO INOX | D19: UNI | E19: 2 | F19: 17340 | G19: =+F19*E19 -> 34680 | H19: 1 | I19: =H19*G19 -> 34680 | J19: 1 | K19: =J19*G19 -> 34680 | L19: =H19-J19 -> 0 | M19: =L19*G19 -> 0
C43: SUB TOTAL | G43: =SUM(G18:G42) -> 34680 | I43: =SUM(I18:I42) -> 34680 | K43: =SUM(K18:K42) -> 34680 | M43: =SUM(M18:M42) -> 0
C44: Retención | I44: =I43*F44 -> 0 | K44: =K43*F44 -> 0 | M44: =M43*F44 -> 0
C45: PAGO RETENCIONES | G45: 0 | H45: 0 | I45: =H45*G45 -> 0 | J45: 0 | K45: =G45*J45 -> 0 | L45: =H45-J45 -> 0 | M45: =L45*G45 -> 0
C46: NETO | G46: =G43-G44+G45 -> 34680 | H46: ru | I46: =+I43-I44 -> 34680 | K46: =+K43-K44 -> 34680 | M46: =+M43-M44 -> 0
C47: 19% VALOR IVA | G47: =G46*19% -> 6589.2 | I47: =I46*19% -> 6589.2 | K47: =K46*19% -> 6589.2 | M47: =+M46*0.19 -> 0
C48: TOTAL | G48: =SUM(G46:G47) -> 41269.2 | I48: =SUM(I46:I47) -> 41269.2 | K48: =SUM(K46:K47) -> 41269.2 | M48: =SUM(M46:M47) -> 0
H56: Constructora MM
