Workbook

Sheet RESUMEN
J3: 1 | L3: al día
J4: 2 | L4: a 15 días
J5: 3 | L5: a 30 días
J6: 4 | L6: a 45 días
J7: 5 | L7: a 60 días
J8: 6 | L8: a 90 días
B9: Obra: | C9: REMODELACION BAÑOS SHC LA CALERA
B10: Dirección: | C10: MALL OPEN PLAZA LA CALERA
B12: PLANILLA DE ESTADOS DE PAGO DE SUBCONTRATOS
B14: Comienzo de Obra: | C14: 45875 | D14: Días de Obra: | E14: =I17-C14 -> 72
B15: Cierre de Obra: | C15: 45935 | D15: Días de Obra | E15: =C15-C14 -> 60 | I15: EEPP#06
I16: PRSENTE | J16: Observación | L16: ACUMULADO | N16: ANTERIORES | P16: Saldo y/o Retención | R16: Avance Financiero | T16: Retención
A17: Nº | B17: SUBCONTRATISTA | C17: RUT | D17: CONCEPTO | E17: CONTRATO | F17: FACTURA | G17: F.pago | H17: Fecha de Pago Oficina | I17: 45947 | R17: % | T17: 0.05
A19: 1 | B19: DPTO 353 CONDOMINIO RAVELLO | C19: 77.944.666-2 | D19: CORREDORA LUZ MARIA CORREA | E19: ='1'!G43 -> 1225000 | F19: CONTRATISTA | I19: ='1'!M43 -> 0 | L19: =+'1'!I43 -> 1225000 | N19: ='1'!K43 -> 1225000 | P19: =E19-L19 -> 0 | R19: =L19/E19 -> 1 | T19: no
A20: 2 | B20: DPTO 752 CONDOMINIO RAVELLO | C20: 11.520.369-K | D20: CORREDORA YARELA YOVANNA | E20: ='2'!G43 -> 1225000 | F20: CONTRATISTA | I20: ='2'!M43 -> 0 | L20: =+'2'!I43 -> 1225000 | N20: ='2'!K43 -> 1225000 | P20: =E20-L20 -> 0 | R20: =L20/E20 -> 1 | T20: no
A21: 3 | B21: FENOLICO EXPRESS | C21: 78007082-K | D21: DIVISIONES FENOLICAS | E21: ='3'!G43 -> 6150000 | F21: CONTRATISTA | G21: 3 | H21: 3 | I21: ='3'!M43 -> 615000 | L21: =+'3'!I43 -> 6150000 | N21: ='3'!K43 -> 5535000 | P21: =E21-L21 -> 0 | R21: =L21/E21 -> 1 | T21: no
A22: 4 | B22: Razón social Fabrica de Muebles LM SPA | C22: 78229023-1 | D22: MUEBLES VANITORIO Y BANCAS | E22: ='4'!G43 -> 4050000 | F22: CONTRATISTA | I22: ='4'!M43 -> 0 | L22: =+'4'!I43 -> 4050000 | N22: ='4'!K43 -> 4050000 | P22: =E22-L22 -> 0 | R22: =L22/E22 -> 1 | T22: no
A23: 5 | B23: JONATHAN PARDO | C23: 18.512.369-3 | D23: GASFITER | E23: ='5'!G45 -> 2415585 | F23: CONTRATISTA | I23: ='5'!M45 -> 0 | L23: =+'5'!I45 -> 2415585 | N23: ='5'!K45 -> 2415585 | P23: =E23-L23 -> 0 | R23: =L23/E23 -> 1 | T23: no
A24: 6 | B24: SERVICIOS DE CONSTRUCCION JADER SPA | C24: 78.037.274-5 | D24: CERAMISTA | E24: ='6'!G48 -> 3071126 | F24: CONTRATISTA | I24: ='6'!M48 -> 0 | L24: =+'6'!I48 -> 3071126 | N24: ='6'!K48 -> 3071126 | P24: =E24-L24 -> 0 | R24: =L24/E24 -> 1 | T24: no
A25: 7 | B25: LUIS URBINA | D25: PINTOR | E25: ='7'!G43 -> 0 | F25: CONTRATISTA | I25: ='7'!M43 -> 0 | L25: =+'3'!I47 -> 0 | N25: ='3'!K47 -> 0 | P25: =E25-L25 -> 0 | R25: =L25/E25 -> #DIV/0!
A26: 8 | B26: Wyg Ingnieria Spa | C26: 77.953.777-3 | D26: ELECTRICO CONEXIÓN CONTENEDO | E26: ='8'!G46 -> 335000 | F26: CONTRATISTA | I26: ='8'!M43 -> 0 | L26: =+'8'!I46 -> 335000 | N26: ='8'!K46 -> 335000 | P26: =E26-L26 -> 0 | R26: =L26/E26 -> 1
A27: 9 | B27: ALEX YAÑEZ | D27: ESPEJOS MARCO DE PUERTA | E27: ='9'!G46 -> 1230000 | F27: CONTRATISTA | I27: ='9'!M43 -> 0 | L27: =+'9'!I46 -> 1230000 | N27: ='9'!K46 -> 1230000 | P27: =E27-L27 -> 0 | R27: =L27/E27 -> 1
B28: TOTAL SUBCONTRATOS | E28: =SUM(E18:E27) -> 19701711 | I28: =SUM(I18:I27) -> 615000 | L28: =SUM(L18:L27) -> 19701711 | M28: =SUM(M18:M27) -> 0 | N28: =SUM(N18:N27) -> 19086711 | P28: =SUM(P18:P27) -> 0 | R28: =L28/E28 -> 1
D30: IVA | E30: =E28*0.19 -> 3743325.1 | G30: IVA | I30: =+I28*0.19 -> 116850
E31: =SUM(E28:E30) -> 23445036 | I31: =SUM(I28:I30) -> 731850
L36: Vº Bº ADMINISTRADOR OBRA

Sheet 1
B3: ESTADO DE PAGO Nº 1
M5: =+RESUMEN!D19 -> CORREDORA LUZ MARIA CORREA
B6: OBRA | C6: =+RESUMEN!C9 -> REMODELACION BAÑOS SHC LA CALERA
B7: UBICACIÓN | C7: =+RESUMEN!C10 -> MALL OPEN PLAZA LA CALERA | M7: Estado de pago
B8: CONTRATISTA | C8: =+RESUMEN!B19 -> DPTO 353 CONDOMINIO RAVELLO | M8: =+RESUMEN!I15 -> EEPP#06
B9: DIRECCION
B10: R.U.T. | C10: =+RESUMEN!C19 -> 77.944.666-2
B11: OC
B13: Monto Contratado a la Fecha | E13: =G40 -> 1225000 | L13: FECHA | M13: =+RESUMEN!I17 -> 45947
G15: TOTAL | H15: Avance Acumulado | J15: Avance E.P. ANTERIOR | L15: Presente
B16: ITEM | C16: DETALLE PARTIDAS | G16: CONTRATO | H16: a la Fecha | L16: Estado de Pago
H17: % | I17: Monto $ | J17: % | K17: Monto $ | L17: % | M17: Monto $
C18: DPTO 353 | D18: UN | E18: CANT | F18: PU
B19: 1 | C19: ARRIENDO MES AGOSTO | D19: GL | E19: 1 | F19: 500000 | G19: =+F19*E19 -> 500000 | H19: 1 | I19: =H19*G19 -> 500000 | J19: 1 | K19: =J19*G19 -> 500000 | L19: =H19-J19 -> 0 | M19: =L19*G19 -> 0
B20: 1.1 | C20: GARANTIÍA | D20: GL | E20: 1 | F20: 500000 | G20: =+F20*E20 -> 500000 | H20: 1 | I20: =H20*G20 -> 500000 | J20: 1 | K20: =J20*G20 -> 500000 | L20: =H20-J20 -> 0 | M20: =L20*G20 -> 0
B21: 1.2 | C21: COMISION CORREDORA | D21: GL | E21: 1 | F21: 225000 | G21: =+F21*E21 -> 225000 | H21: 1 | I21: =H21*G21 -> 225000 | J21: 1 | K21: =J21*G21 -> 225000 | L21: =H21-J21 -> 0 | M21: =L21*G21 -> 0
B22: 1.3 | C22: ARRIENDO MES SEPTIEMBRE | D22: GL | E22: 1 | F22: 500000 | G22: =+F22*E22 -> 500000 | H22: 1 | I22: =H22*G22 -> 500000 | J22: 1 | K22: =J22*G22 -> 500000 | L22: =H22-J22 -> 0 | M22: =L22*G22 -> 0
C24: DEVOLUCION DE GARANTIA | D24: GL | E24: -1 | F24: 500000 | G24: =+F24*E24 -> -500000 | H24: 1 | I24: =H24*G24 -> -500000 | J24: 1 | K24: =J24*G24 -> -500000 | L24: =H24-J24 -> 0 | M24: =L24*G24 -> 0
C26: SERVICIOS SE DESCUENTAN DE GARANTIA
C40: SUB TOTAL | G40: =SUM(G18:G39) -> 1225000 | I40: =SUM(I18:I39) -> 1225000 | K40: =SUM(K18:K39) -> 1225000 | M40: =SUM(M18:M39) -> 0
C41: Retención | I41: =I40*F41 -> 0 | K41: =K40*F41 -> 0 | M41: =M40*F41 -> 0
C42: PAGO RETENCIONES | G42: 0 | H42: 0 | I42: =H42*G42 -> 0 | J42: 0 | K42: =G42*J42 -> 0 | L42: =H42-J42 -> 0 | M42: =L42*G42 -> 0
C43: NETO | G43: =G40-G41+G42 -> 1225000 | H43: ru | I43: =+I40-I41 -> 1225000 | K43: =+K40-K41 -> 1225000 | M43: =+M40-M41 -> 0
C44: 19% VALOR IVA | G44: =G43*19% -> 232750 | I44: =I43*19% -> 232750 | K44: =K43*19% -> 232750 | M44: =+M43*0.19 -> 0
C45: TOTAL | G45: =SUM(G43:G44) -> 1457750 | I45: =SUM(I43:I44) -> 1457750 | K45: =SUM(K43:K44) -> 1457750 | M45: =SUM(M43:M44) -> 0
H53: Constructora MM

Sheet 2
B3: ESTADO DE PAGO Nº 1
M5: =+RESUMEN!D19 -> CORREDORA LUZ MARIA CORREA
B6: OBRA | C6: =+RESUMEN!C9 -> REMODELACION BAÑOS SHC LA CALERA
B7: UBICACIÓN | C7: =+RESUMEN!C10 -> MALL OPEN PLAZA LA CALERA | M7: Estado de pago
B8: CONTRATISTA | C8: =+RESUMEN!B20 -> DPTO 752 CONDOMINIO RAVELLO | M8: =+RESUMEN!I15 -> EEPP#06
B9: DIRECCION
B10: R.U.T. | C10: =+RESUMEN!C20 -> 11.520.369-K
B11: OC
B13: Monto Contratado a la Fecha | E13: =G40 -> 1225000 | L13: FECHA | M13: =+RESUMEN!I17 -> 45947
G15: TOTAL | H15: Avance Acumulado | J15: Avance E.P. ANTERIOR | L15: Presente
B16: ITEM | C16: DETALLE PARTIDAS | G16: CONTRATO | H16: a la Fecha | L16: Estado de Pago
H17: % | I17: Monto $ | J17: % | K17: Monto $ | L17: % | M17: Monto $
C18: DPTO 752 | D18: UN | E18: CANT | F18: PU
B19: 1 | C19: ARRIENDO MES AGOSTO | D19: GL | E19: 1 | F19: 500000 | G19: =+F19*E19 -> 500000 | H19: 1 | I19: =H19*G19 -> 500000 | J19: 1 | K19: =J19*G19 -> 500000 | L19: =H19-J19 -> 0 | M19: =L19*G19 -> 0
B20: 1.1 | C20: GARANTIÍA | D20: GL | E20: 1 | F20: 500000 | G20: =+F20*E20 -> 500000 | H20: 1 | I20: =H20*G20 -> 500000 | J20: 1 | K20: =J20*G20 -> 500000 | L20: =H20-J20 -> 0 | M20: =L20*G20 -> 0
B21: 1.2 | C21: COMISION CORREDORA | D21: GL | E21: 1 | F21: 225000 | G21: =+F21*E21 -> 225000 | H21: 1 | I21: =H21*G21 -> 225000 | J21: 1 | K21: =J21*G21 -> 225000 | L21: =H21-J21 -> 0 | M21: =L21*G21 -> 0
B22: 1.3 | C22: ARRIENDO MES SEPTIOEMBRE | D22: GL | E22: 1 | F22: 500000 | G22: =+F22*E22 -> 500000 | H22: 1 | I22: =H22*G22 -> 500000 | J22: 1 | K22: =J22*G22 -> 500000 | L22: =H22-J22 -> 0 | M22: =L22*G22 -> 0
C24: DEVOLUCION DE GARANTIA | D24: GL | E24: -1 | F24: 500000 | G24: =+F24*E24 -> -500000 | H24: 1 | I24: =H24*G24 -> -500000 | J24: 1 | K24: =J24*G24 -> -500000 | L24: =H24-J24 -> 0 | M24: =L24*G24 -> 0
C26: SERVICIOS SE DESCUENTAN DE GARANTIA
C40: SUB TOTAL | G40: =SUM(G18:G39) -> 1225000 | I40: =SUM(I18:I39) -> 1225000 | K40: =SUM(K18:K39) -> 1225000 | M40: =SUM(M18:M39) -> 0
C41: Retención | I41: =I40*F41 -> 0 | K41: =K40*F41 -> 0 | M41: =M40*F41 -> 0
C42: PAGO RETENCIONES | G42: 0 | H42: 0 | I42: =H42*G42 -> 0 | J42: 0 | K42: =G42*J42 -> 0 | L42: =H42-J42 -> 0 | M42: =L42*G42 -> 0
C43: NETO | G43: =G40-G41+G42 -> 1225000 | H43: ru | I43: =+I40-I41 -> 1225000 | K43: =+K40-K41 -> 1225000 | M43: =+M40-M41 -> 0
C44: 19% VALOR IVA | G44: =G43*19% -> 232750 | I44: =I43*19% -> 232750 | K44: =K43*19% -> 232750 | M44: =+M43*0.19 -> 0
C45: TOTAL | G45: =SUM(G43:G44) -> 1457750 | I45: =SUM(I43:I44) -> 1457750 | K45: =SUM(K43:K44) -> 1457750 | M45: =SUM(M43:M44) -> 0
H53: Constructora MM

Sheet 3
B3: ESTADO DE PAGO Nº 1
M5: =+RESUMEN!D19 -> CORREDORA LUZ MARIA CORREA
B6: OBRA | C6: =+RESUMEN!C9 -> REMODELACION BAÑOS SHC LA CALERA
B7: UBICACIÓN | C7: =+RESUMEN!C10 -> MALL OPEN PLAZA LA CALERA | M7: Estado de pago
B8: CONTRATISTA | C8: =+RESUMEN!B20 -> DPTO 752 CONDOMINIO RAVELLO | M8: =+RESUMEN!I15 -> EEPP#06
B9: DIRECCION
B10: R.U.T. | C10: =+RESUMEN!C20 -> 11.520.369-K
B11: OC
B13: Monto Contratado a la Fecha | E13: =G40 -> 6150000 | L13: FECHA | M13: =+RESUMEN!I17 -> 45947
G15: TOTAL | H15: Avance Acumulado | J15: Avance E.P. ANTERIOR | L15: Presente
B16: ITEM | C16: DETALLE PARTIDAS | G16: CONTRATO | H16: a la Fecha | L16: Estado de Pago
H17: % | I17: Monto $ | J17: % | K17: Monto $ | L17: % | M17: Monto $
C18: DPTO 752 | D18: UN | E18: CANT | F18: PU
B19: 1 | C19: Cubículos de WC en fenólico solido de 19 mm color blanco con su respectiva herrajeria en acero inoxidable | D19: UNI | E19: 9 | F19: 470000 | G19: =+F19*E19 -> 4230000 | H19: 1 | I19: =H19*G19 -> 4230000 | J19: 0.9 | K19: =J19*G19 -> 3807000 | L19: =H19-J19 -> 0.1 | M19: =L19*G19 -> 423000
B20: 1.1 | C20: Puertas de ducha en fenólico solido de 19mm color blanco con su respectiva herrajeria en acero inoxidable | D20: GL | E20: 10 | F20: 160000 | G20: =+F20*E20 -> 1600000 | H20: 1 | I20: =H20*G20 -> 1600000 | J20: 0.9 | K20: =J20*G20 -> 1440000 | L20: =H20-J20 -> 0.1 | M20: =L20*G20 -> 160000
B21: 1.2 | C21: Divisores de urinario en fenólico solido color blanco de 19mm | D21: GL | E21: 2 | F21: 80000 | G21: =+F21*E21 -> 160000 | H21: 1 | I21: =H21*G21 -> 160000 | J21: 0.9 | K21: =J21*G21 -> 144000 | L21: =H21-J21 -> 0.1 | M21: =L21*G21 -> 16000
B22: 1.3 | C22: Flete | D22: GL | E22: 1 | F22: 160000 | G22: =+F22*E22 -> 160000 | H22: 1 | I22: =H22*G22 -> 160000 | J22: 0.9 | K22: =J22*G22 -> 144000 | L22: =H22-J22 -> 0.1 | M22: =L22*G22 -> 16000
C40: SUB TOTAL | G40: =SUM(G18:G39) -> 6150000 | I40: =SUM(I18:I39) -> 6150000 | K40: =SUM(K18:K39) -> 5535000 | M40: =SUM(M18:M39) -> 615000
C41: Retención | I41: =I40*F41 -> 0 | K41: =K40*F41 -> 0 | M41: =M40*F41 -> 0
C42: PAGO RETENCIONES | G42: 0 | H42: 0 | I42: =H42*G42 -> 0 | J42: 0 | K42: =G42*J42 -> 0 | L42: =H42-J42 -> 0 | M42: =L42*G42 -> 0
C43: NETO | G43: =G40-G41+G42 -> 6150000 | H43: ru | I43: =+I40-I41 -> 6150000 | K43: =+K40-K41 -> 5535000 | M43: =+M40-M41 -> 615000
C44: 19% VALOR IVA | G44: =G43*19% -> 1168500 | I44: =I43*19% -> 1168500 | K44: =K43*19% -> 1051650 | M44: =+M43*0.19 -> 116850
C45: TOTAL | G45: =SUM(G43:G44) -> 7318500 | I45: =SUM(I43:I44) -> 7318500 | K45: =SUM(K43:K44) -> 6586650 | M45: =SUM(M43:M44) -> 731850
H53: Constructora MM

Sheet 4
B3: ESTADO DE PAGO Nº 1
M5: =+RESUMEN!D19 -> CORREDORA LUZ MARIA CORREA
B6: OBRA | C6: =+RESUMEN!C9 -> REMODELACION BAÑOS SHC LA CALERA
B7: UBICACIÓN | C7: =+RESUMEN!C10 -> MALL OPEN PLAZA LA CALERA | M7: Estado de pago
B8: CONTRATISTA | C8: =+RESUMEN!B20 -> DPTO 752 CONDOMINIO RAVELLO | M8: =+RESUMEN!I15 -> EEPP#06
B9: DIRECCION
B10: R.U.T. | C10: =+RESUMEN!C20 -> 11.520.369-K
B11: OC
B13: Monto Contratado a la Fecha | E13: =G40 -> 4050000 | L13: FECHA | M13: =+RESUMEN!I17 -> 45947
G15: TOTAL | H15: Avance Acumulado | J15: Avance E.P. ANTERIOR | L15: Presente
B16: ITEM | C16: DETALLE PARTIDAS | G16: CONTRATO | H16: a la Fecha | L16: Estado de Pago
H17: % | I17: Monto $ | J17: % | K17: Monto $ | L17: % | M17: Monto $
D18: UN | E18: CANT | F18: PU
B19: 1 | C19: Puerta en tipo placarol con bastidor | D19: UNI | E19: 2 | F19: 185000 | G19: =+F19*E19 -> 370000 | H19: 1 | I19: =H19*G19 -> 370000 | J19: 1 | K19: =J19*G19 -> 370000 | L19: =H19-J19 -> 0 | M19: =L19*G19 -> 0
C20: de madera pino finger.
C21: con tapa en mdf. De 5,5mm.
C22: revestidas en lamitech standard
C23: color Mouse 2193.
C24: no incluye marco
C26: Cubierta de granito gris mara con | D26: UNI | E26: 2 | F26: 1170000 | G26: =+F26*E26 -> 2340000 | H26: 1 | I26: =H26*G26 -> 2340000 | J26: 1 | K26: =J26*G26 -> 2340000 | L26: =H26-J26 -> 0 | M26: =L26*G26 -> 0
C27: faldon de 15cm respaldo de 10
C28: no incluye vanitorios
C29: incluye perforaciones para vanitorios
C30: Banca
C31: Base estructura metálica
C32: con cubierta en madera pino barnizada
C33: Banca en L | D33: UNI | E33: 3 | F33: 260000 | G33: =+F33*E33 -> 780000 | H33: 1 | I33: =H33*G33 -> 780000 | J33: 1 | K33: =J33*G33 -> 780000 | L33: =H33-J33 -> 0 | M33: =L33*G33 -> 0
C34: BANCA | D34: UNI | E34: 1 | F34: 380000 | G34: =+F34*E34 -> 380000 | H34: 1 | I34: =H34*G34 -> 380000 | J34: 1 | K34: =J34*G34 -> 380000 | L34: =H34-J34 -> 0 | M34: =L34*G34 -> 0
C35: BANCA | D35: UNI | E35: 1 | F35: 90000 | G35: =+F35*E35 -> 90000 | H35: 1 | I35: =H35*G35 -> 90000 | J35: 1 | K35: =J35*G35 -> 90000 | L35: =H35-J35 -> 0 | M35: =L35*G35 -> 0
C36: Instalación la Calera | D36: UNI | E36: 1 | F36: 250000 | G36: =+F36*E36 -> 250000 | H36: 1 | I36: =H36*G36 -> 250000 | J36: 1 | K36: =J36*G36 -> 250000 | L36: =H36-J36 -> 0 | M36: =L36*G36 -> 0
C37: DESCUENTO | D37: UNI | E37: -1 | F37: 160000 | G37: =+F37*E37 -> -160000 | H37: 1 | I37: =H37*G37 -> -160000 | J37: 1 | K37: =J37*G37 -> -160000 | L37: =H37-J37 -> 0 | M37: =L37*G37 -> 0
C40: SUB TOTAL | G40: =SUM(G18:G39) -> 4050000 | I40: =SUM(I18:I39) -> 4050000 | K40: =SUM(K18:K39) -> 4050000 | M40: =SUM(M18:M39) -> 0
C41: Retención | I41: =I40*F41 -> 0 | K41: =K40*F41 -> 0 | M41: =M40*F41 -> 0
C42: PAGO RETENCIONES | G42: 0 | H42: 0 | I42: =H42*G42 -> 0 | J42: 0 | K42: =G42*J42 -> 0 | L42: =H42-J42 -> 0 | M42: =L42*G42 -> 0
C43: NETO | G43: =G40-G41+G42 -> 4050000 | H43: ru | I43: =+I40-I41 -> 4050000 | K43: =+K40-K41 -> 4050000 | M43: =+M40-M41 -> 0
C44: 19% VALOR IVA | G44: =G43*19% -> 769500 | I44: =I43*19% -> 769500 | K44: =K43*19% -> 769500 | M44: =+M43*0.19 -> 0
C45: TOTAL | G45: =SUM(G43:G44) -> 4819500 | I45: =SUM(I43:I44) -> 4819500 | K45: =SUM(K43:K44) -> 4819500 | M45: =SUM(M43:M44) -> 0
H53: Constructora MM

Sheet 5
B3: ESTADO DE PAGO Nº 1
M5: =+RESUMEN!D19 -> CORREDORA LUZ MARIA CORREA
B6: OBRA | C6: =+RESUMEN!C9 -> REMODELACION BAÑOS SHC LA CALERA
B7: UBICACIÓN | C7: =+RESUMEN!C10 -> MALL OPEN PLAZA LA CALERA | M7: Estado de pago
B8: CONTRATISTA | C8: =+RESUMEN!B20 -> DPTO 752 CONDOMINIO RAVELLO | M8: =+RESUMEN!I15 -> EEPP#06
B9: DIRECCION
B10: R.U.T. | C10: =+RESUMEN!C20 -> 11.520.369-K
B11: OC
B13: Monto Contratado a la Fecha | E13: =G42 -> 2415585 | L13: FECHA | M13: =+RESUMEN!I17 -> 45947
G15: TOTAL | H15: Avance Acumulado | J15: Avance E.P. ANTERIOR | L15: Presente
B16: ITEM | C16: DETALLE PARTIDAS | G16: CONTRATO | H16: a la Fecha | L16: Estado de Pago
H17: % | I17: Monto $ | J17: % | K17: Monto $ | L17: % | M17: Monto $
D18: UN | E18: CANT | F18: PU
B19: 1 | C19: Suministro e instalación de Vanitorio cubierta de placa lisa de granito gris MARA o similar. Receptáculo modelo GEBBO marca WASSER. Montado sobre estructura metálica. | D19: UNI | E19: 10 | F19: 31000 | G19: =+F19*E19 -> 310000 | H19: 1 | I19: =H19*G19 -> 310000 | J19: 1 | K19: =J19*G19 -> 310000 | L19: =H19-J19 -> 0 | M19: =L19*G19 -> 0
C20: Urinario mural suspendido de porcelana vitrificada modelo Nette marca Wasser. Sifón botella para urinario cromado de wasser. Desagüe para urinario Stil de wasser. | E20: 3 | F20: 67000 | G20: =+F20*E20 -> 201000 | H20: 1 | I20: =H20*G20 -> 201000 | J20: 1 | K20: =J20*G20 -> 201000 | L20: =H20-J20 -> 0 | M20: =L20*G20 -> 0
C21: Fluxor tubo recto para urinario modelo KOLBEN código CW1001000 de WASSER | E21: 3 | F21: 67000 | G21: =+F21*E21 -> 201000 | H21: 1 | I21: =H21*G21 -> 201000 | J21: 1 | K21: =J21*G21 -> 201000 | L21: =H21-J21 -> 0 | M21: =L21*G21 -> 0
C22: W.C. de arrastre para fluxor expuesto, modelo WIDDER 2 código HU2021001 marca WASSER | E22: 9 | F22: 42300 | G22: =+F22*E22 -> 380700 | H22: 1 | I22: =H22*G22 -> 380700 | J22: 1 | K22: =J22*G22 -> 380700 | L22: =H22-J22 -> 0 | M22: =L22*G22 -> 0
C23: Fluxor expuesto LEREN II WF 6000000 | E23: 9 | F23: 42300 | G23: =+F23*E23 -> 380700 | H23: 1 | I23: =H23*G23 -> 380700 | J23: 1 | K23: =J23*G23 -> 380700 | L23: =H23-J23 -> 0 | M23: =L23*G23 -> 0
C24: Ducha Antivandálica modelo Lange Weigen Marca Wasser y mezclador temporizador. | E24: 10 | F24: 50000 | G24: =+F24*E24 -> 500000 | H24: 1 | I24: =H24*G24 -> 500000 | J24: 1 | K24: =J24*G24 -> 500000 | L24: =H24-J24 -> 0 | M24: =L24*G24 -> 0
C25: Grifería temporizada Bojen Mix de wasser | E25: 10 | F25: 29000 | G25: =+F25*E25 -> 290000 | H25: 1 | I25: =H25*G25 -> 290000 | J25: 1 | K25: =J25*G25 -> 290000 | L25: =H25-J25 -> 0 | M25: =L25*G25 -> 0
C26: Termo 400lts baño de mujeres (sólo M.O) | D26: UNI | E26: 1 | F26: 311000 | G26: =+F26*E26 -> 311000 | H26: 1 | I26: =H26*G26 -> 311000 | J26: 1 | K26: =J26*G26 -> 311000 | L26: =H26-J26 -> 0 | M26: =L26*G26 -> 0
C27: Desague duchas | E27: 10 | F27: 31000 | G27: =+F27*E27 -> 310000 | H27: 1 | I27: =H27*G27 -> 310000 | J27: 1 | K27: =J27*G27 -> 310000 | L27: =H27-J27 -> 0 | M27: =L27*G27 -> 0
C30: DESCUENTO por cierre | D30: GL | E30: -1 | F30: 200000 | G30: =+F30*E30 -> -200000 | H30: 1 | I30: =H30*G30 -> -200000 | J30: 1 | K30: =J30*G30 -> -200000 | L30: =H30-J30 -> 0 | M30: =L30*G30 -> 0
C33: sueldo Agosto | D33: gl | E33: -1 | F33: 93333 | G33: =+F33*E33 -> -93333 | H33: 1 | I33: =H33*G33 -> -93333 | J33: 1 | K33: =J33*G33 -> -93333 | L33: =H33-J33 -> 0 | M33: =L33*G33 -> 0
C34: cotizaciones Agosto | D34: gl | E34: -1 | F34: 19766 | G34: =+F34*E34 -> -19766 | H34: 1 | I34: =H34*G34 -> -19766 | J34: 1 | K34: =J34*G34 -> -19766 | L34: =H34-J34 -> 0 | M34: =L34*G34 -> 0
C35: diferencia informada mes de agosto | D35: gl | E35: -1 | F35: 10716 | G35: =+F35*E35 -> -10716 | H35: 1 | I35: =H35*G35 -> -10716 | J35: 1 | K35: =J35*G35 -> -10716 | L35: =H35-J35 -> 0 | M35: =L35*G35 -> 0
C37: sueldo y cotizaciones Septiembre | D37: gl | E37: -1 | F37: 145000 | G37: =+F37*E37 -> -145000 | H37: 1 | I37: =H37*G37 -> -145000 | J37: 1 | K37: =J37*G37 -> -145000 | L37: =H37-J37 -> 0 | M37: =L37*G37 -> 0
C42: SUB TOTAL | G42: =SUM(G18:G41) -> 2415585 | I42: =SUM(I18:I41) -> 2415585 | K42: =SUM(K18:K41) -> 2415585 | M42: =SUM(M18:M41) -> 0
C43: Retención | I43: =I42*F43 -> 0 | K43: =K42*F43 -> 0 | M43: =M42*F43 -> 0
C44: PAGO RETENCIONES | G44: 0 | H44: 0 | I44: =H44*G44 -> 0 | J44: 0 | K44: =G44*J44 -> 0 | L44: =H44-J44 -> 0 | M44: =L44*G44 -> 0
C45: NETO | G45: =G42-G43+G44 -> 2415585 | H45: ru | I45: =+I42-I43 -> 2415585 | K45: =+K42-K43 -> 2415585 | M45: =+M42-M43 -> 0
C46: 19% VALOR IVA | G46: =G45*19% -> 458961.15 | I46: =I45*19% -> 458961.15 | K46: =K45*19% -> 458961.15 | M46: =+M45*0.19 -> 0
C47: TOTAL | G47: =SUM(G45:G46) -> 2874546.1 | I47: =SUM(I45:I46) -> 2874546.1 | K47: =SUM(K45:K46) -> 2874546.1 | M47: =SUM(M45:M46) -> 0
H55: Constructora MM

Sheet 6
B3: ESTADO DE PAGO Nº 1
M5: =+RESUMEN!D19 -> CORREDORA LUZ MARIA CORREA
B6: OBRA | C6: =+RESUMEN!C9 -> REMODELACION BAÑOS SHC LA CALERA
B7: UBICACIÓN | C7: =+RESUMEN!C10 -> MALL OPEN PLAZA LA CALERA | M7: Estado de pago
B8: CONTRATISTA | C8: =+RESUMEN!B20 -> DPTO 752 CONDOMINIO RAVELLO | M8: =+RESUMEN!I15 -> EEPP#06
B9: DIRECCION
B10: R.U.T. | C10: =+RESUMEN!C20 -> 11.520.369-K
B11: OC
B13: Monto Contratado a la Fecha | E13: =G45 -> 3071126 | L13: FECHA | M13: =+RESUMEN!I17 -> 45947
G15: TOTAL | H15: Avance Acumulado | J15: Avance E.P. ANTERIOR | L15: Presente
B16: ITEM | C16: DETALLE PARTIDAS | G16: CONTRATO | H16: a la Fecha | L16: Estado de Pago
H17: % | I17: Monto $ | J17: % | K17: Monto $ | L17: % | M17: Monto $
D18: UN | E18: CANT | F18: PU
B19: 1 | C19: Suministro e instalación de porcelanato 60x60, color gris, de HOLZTEK modelo Rustico SKU 261960-1. Instalado con adhesivo tipo Bekron | D19: UNI | E19: 88.98 | F19: 9500 | G19: =+F19*E19 -> 845310 | H19: 1 | I19: =H19*G19 -> 845310 | J19: 1 | K19: =J19*G19 -> 845310 | L19: =H19-J19 -> 0 | M19: =L19*G19 -> 0
C20: Suministro e instalación de cerámica esmaltada en muros 30x60cm, color blanco brillante, de HOLZTEK SKU:231112-7. Instalado con adhesivo bekron muros. | D20: M2 | E20: 194.1 | F20: 8000 | G20: =+F20*E20 -> 1552800 | H20: 1 | I20: =H20*G20 -> 1552800 | J20: 1 | K20: =J20*G20 -> 1552800 | L20: =H20-J20 -> 0 | M20: =L20*G20 -> 0
C21: COMIDA Y TRASLADO | D21: GL | E21: 1 | F21: 400000 | G21: =+F21*E21 -> 400000 | H21: 1 | I21: =H21*G21 -> 400000 | J21: 1 | K21: =J21*G21 -> 400000 | L21: =H21-J21 -> 0 | M21: =L21*G21 -> 0
C22: 'Suministro e instalación de canto de PVC típica para cerámica (va en todos los bordes). | D22: ML | E22: 132.5 | F22: 2000 | G22: =+F22*E22 -> 265000 | H22: 1 | I22: =H22*G22 -> 265000 | J22: 1 | K22: =J22*G22 -> 265000 | L22: =H22-J22 -> 0 | M22: =L22*G22 -> 0
C23: ML porcelanato y ceramica | D23: ML | E23: 1 | F23: 200000 | G23: =+F23*E23 -> 200000 | H23: 1 | I23: =H23*G23 -> 200000 | J23: 1 | K23: =J23*G23 -> 200000 | L23: =H23-J23 -> 0 | M23: =L23*G23 -> 0
C26: DIFERENCIA DE M2 INSTALADO VS CANTIDAD ITEMIZADO | D26: M2 | E26: 63.78 | F26: 8000 | G26: =+F26*E26 -> 510240 | H26: 1 | I26: =H26*G26 -> 510240 | J26: 1 | K26: =J26*G26 -> 510240 | L26: =H26-J26 -> 0 | M26: =L26*G26 -> 0
C31: DESCUENTO | D31: GL | E31: -1 | F31: 163110 | G31: =+F31*E31 -> -163110 | H31: 1 | I31: =H31*G31 -> -163110 | J31: 1 | K31: =J31*G31 -> -163110 | L31: =H31-J31 -> 0 | M31: =L31*G31 -> 0
C33: DESCUENTO sueldo JADER | D33: GL | E33: -1 | F33: 93333 | G33: =+F33*E33 -> -93333 | H33: 1 | I33: =H33*G33 -> -93333 | J33: 1 | K33: =J33*G33 -> -93333 | L33: =H33-J33 -> 0 | M33: =L33*G33 -> 0
C34: DESCUENTO cotizaciones JADER | D34: GL | E34: -1 | F34: 19766 | G34: =+F34*E34 -> -19766 | H34: 1 | I34: =H34*G34 -> -19766 | J34: 1 | K34: =J34*G34 -> -19766 | L34: =H34-J34 -> 0 | M34: =L34*G34 -> 0
C36: DESCUENTO sueldo MANUEL | D36: GL | E36: -1 | F36: 93333 | G36: =+F36*E36 -> -93333 | H36: 1 | I36: =H36*G36 -> -93333 | J36: 1 | K36: =J36*G36 -> -93333 | L36: =H36-J36 -> 0 | M36: =L36*G36 -> 0
C37: DESCUENTO cotizaciones MANUEL | D37: GL | E37: -1 | F37: 19766 | G37: =+F37*E37 -> -19766 | H37: 1 | I37: =H37*G37 -> -19766 | J37: 1 | K37: =J37*G37 -> -19766 | L37: =H37-J37 -> 0 | M37: =L37*G37 -> 0
C38: DIFERENCIA DE ENTRE SUELDOS Y COTIZACIONES AGOSTO | D38: GL | E38: -1 | F38: 22916 | G38: =+F38*E38 -> -22916 | H38: 1 | I38: =H38*G38 -> -22916 | J38: 1 | K38: =J38*G38 -> -22916 | L38: =H38-J38 -> 0 | M38: =L38*G38 -> 0
C41: DESCUENTOS SUELDO MES DE SEPTIEMBRE | D41: GL | E41: -2 | F41: 145000 | G41: =+F41*E41 -> -290000 | H41: 1 | I41: =H41*G41 -> -290000 | J41: 1 | K41: =J41*G41 -> -290000 | L41: =H41-J41 -> 0 | M41: =L41*G41 -> 0
C45: SUB TOTAL | G45: =SUM(G18:G44) -> 3071126 | I45: =SUM(I18:I44) -> 3071126 | K45: =SUM(K18:K44) -> 3071126 | M45: =SUM(M18:M44) -> 0
C46: Retención | I46: =I45*F46 -> 0 | K46: =K45*F46 -> 0 | M46: =M45*F46 -> 0
C47: PAGO RETENCIONES | G47: 0 | H47: 0 | I47: =H47*G47 -> 0 | J47: 0 | K47: =G47*J47 -> 0 | L47: =H47-J47 -> 0 | M47: =L47*G47 -> 0
C48: NETO | G48: =G45-G46+G47 -> 3071126 | H48: ru | I48: =+I45-I46 -> 3071126 | K48: =+K45-K46 -> 3071126 | M48: =+M45-M46 -> 0
C49: 19% VALOR IVA | G49: =G48*19% -> 583513.94 | I49: =I48*19% -> 583513.94 | K49: =K48*19% -> 583513.94 | M49: =+M48*0.19 -> 0
C50: TOTAL | G50: =SUM(G48:G49) -> 3654639.9 | I50: =SUM(I48:I49) -> 3654639.9 | K50: =SUM(K48:K49) -> 3654639.9 | M50: =SUM(M48:M49) -> 0
H58: Constructora MM

Sheet 7
B3: ESTADO DE PAGO Nº 1
M5: =+RESUMEN!D19 -> CORREDORA LUZ MARIA CORREA
B6: OBRA | C6: =+RESUMEN!C9 -> REMODELACION BAÑOS SHC LA CALERA
B7: UBICACIÓN | C7: =+RESUMEN!C10 -> MALL OPEN PLAZA LA CALERA | M7: Estado de pago
B8: CONTRATISTA | C8: =+RESUMEN!B20 -> DPTO 752 CONDOMINIO RAVELLO | M8: =+RESUMEN!I15 -> EEPP#06
B9: DIRECCION
B10: R.U.T. | C10: =+RESUMEN!C20 -> 11.520.369-K
B11: OC
B13: Monto Contratado a la Fecha | E13: =G40 -> 0 | L13: FECHA | M13: =+RESUMEN!I17 -> 45947
G15: TOTAL | H15: Avance Acumulado | J15: Avance E.P. ANTERIOR | L15: Presente
B16: ITEM | C16: DETALLE PARTIDAS | G16: CONTRATO | H16: a la Fecha | L16: Estado de Pago
H17: % | I17: Monto $ | J17: % | K17: Monto $ | L17: % | M17: Monto $
D18: UN | E18: CANT | F18: PU
B19: 1 | G19: =+F19*E19 -> 0 | H19: 0 | I19: =H19*G19 -> 0 | J19: 0 | K19: =J19*G19 -> 0 | L19: =H19-J19 -> 0 | M19: =L19*G19 -> 0
G20: =+F20*E20 -> 0 | H20: 0 | I20: =H20*G20 -> 0 | J20: 0 | K20: =J20*G20 -> 0 | L20: =H20-J20 -> 0 | M20: =L20*G20 -> 0
G21: =+F21*E21 -> 0 | H21: 0 | I21: =H21*G21 -> 0 | J21: 0 | K21: =J21*G21 -> 0 | L21: =H21-J21 -> 0 | M21: =L21*G21 -> 0
G22: =+F22*E22 -> 0 | H22: 0 | I22: =H22*G22 -> 0 | J22: 0 | K22: =J22*G22 -> 0 | L22: =H22-J22 -> 0 | M22: =L22*G22 -> 0
G23: =+F23*E23 -> 0 | H23: 0 | I23: =H23*G23 -> 0 | J23: 0 | K23: =J23*G23 -> 0 | L23: =H23-J23 -> 0 | M23: =L23*G23 -> 0
C40: SUB TOTAL | G40: =SUM(G18:G39) -> 0 | I40: =SUM(I18:I39) -> 0 | K40: =SUM(K18:K39) -> 0 | M40: =SUM(M18:M39) -> 0
C41: Retención | I41: =I40*F41 -> 0 | K41: =K40*F41 -> 0 | M41: =M40*F41 -> 0
C42: PAGO RETENCIONES | G42: 0 | H42: 0 | I42: =H42*G42 -> 0 | J42: 0 | K42: =G42*J42 -> 0 | L42: =H42-J42 -> 0 | M42: =L42*G42 -> 0
C43: NETO | G43: =G40-G41+G42 -> 0 | H43: ru | I43: =+I40-I41 -> 0 | K43: =+K40-K41 -> 0 | M43: =+M40-M41 -> 0
C44: 19% VALOR IVA | G44: =G43*19% -> 0 | I44: =I43*19% -> 0 | K44: =K43*19% -> 0 | M44: =+M43*0.19 -> 0
C45: TOTAL | G45: =SUM(G43:G44) -> 0 | I45: =SUM(I43:I44) -> 0 | K45: =SUM(K43:K44) -> 0 | M45: =SUM(M43:M44) -> 0
H53: Constructora MM

Sheet 8
B3: ESTADO DE PAGO Nº 1
M5: =+RESUMEN!D19 -> CORREDORA LUZ MARIA CORREA
B6: OBRA | C6: =+RESUMEN!C9 -> REMODELACION BAÑOS SHC LA CALERA
B7: UBICACIÓN | C7: =+RESUMEN!C10 -> MALL OPEN PLAZA LA CALERA | M7: Estado de pago
B8: CONTRATISTA | C8: =+RESUMEN!B20 -> DPTO 752 CONDOMINIO RAVELLO | M8: =+RESUMEN!I15 -> EEPP#06
B9: DIRECCION
B10: R.U.T. | C10: =+RESUMEN!C20 -> 11.520.369-K
B11: OC
B13: Monto Contratado a la Fecha | E13: =G43 -> 335000 | L13: FECHA | M13: =+RESUMEN!I17 -> 45947
G15: TOTAL | H15: Avance Acumulado | J15: Avance E.P. ANTERIOR | L15: Presente
B16: ITEM | C16: DETALLE PARTIDAS | G16: CONTRATO | H16: a la Fecha | L16: Estado de Pago
H17: % | I17: Monto $ | J17: % | K17: Monto $ | L17: % | M17: Monto $
D18: UN | E18: CANT | F18: PU
B19: 1 | C19: CONEXIÓN DE CONTENEDOR Y TABLERO ELECTRICO CON REMARCADOR. INCLUYE CORDO ELECTRICO Y MATERIALES | D19: UNI | E19: 1 | F19: 140000 | G19: =+F19*E19 -> 140000 | H19: 1 | I19: =H19*G19 -> 140000 | J19: 1 | K19: =J19*G19 -> 140000 | L19: =H19-J19 -> 0 | M19: =L19*G19 -> 0
C20: COMPRA DE REMARCADO | D20: UNI | E20: 1 | F20: 40000 | G20: =+F20*E20 -> 40000 | H20: 1 | I20: =H20*G20 -> 40000 | J20: 1 | K20: =J20*G20 -> 40000 | L20: =H20-J20 -> 0 | M20: =L20*G20 -> 0
C21: 2DO TRASLADO POR INSTALACION DE REMARCADOR | D21: UNI | E21: 1 | F21: 55000 | G21: =+F21*E21 -> 55000 | H21: 1 | I21: =H21*G21 -> 55000 | J21: 1 | K21: =J21*G21 -> 55000 | L21: =H21-J21 -> 0 | M21: =L21*G21 -> 0
C23: DESCONEXION DE TABLERO Y CONEXIÓN DE TERMO | D23: GL | E23: 1 | F23: 100000 | G23: =+F23*E23 -> 100000 | H23: 1 | I23: =H23*G23 -> 100000 | J23: 1 | K23: =J23*G23 -> 100000 | L23: =H23-J23 -> 0 | M23: =L23*G23 -> 0
C24: INCLUYE TRASLADO
C43: SUB TOTAL | G43: =SUM(G18:G42) -> 335000 | I43: =SUM(I18:I42) -> 335000 | K43: =SUM(K18:K42) -> 335000 | M43: =SUM(M18:M42) -> 0
C44: Retención | I44: =I43*F44 -> 0 | K44: =K43*F44 -> 0 | M44: =M43*F44 -> 0
C45: PAGO RETENCIONES | G45: 0 | H45: 0 | I45: =H45*G45 -> 0 | J45: 0 | K45: =G45*J45 -> 0 | L45: =H45-J45 -> 0 | M45: =L45*G45 -> 0
C46: NETO | G46: =G43-G44+G45 -> 335000 | H46: ru | I46: =+I43-I44 -> 335000 | K46: =+K43-K44 -> 335000 | M46: =+M43-M44 -> 0
C47: 19% VALOR IVA | G47: =G46*19% -> 63650 | I47: =I46*19% -> 63650 | K47: =K46*19% -> 63650 | M47: =+M46*0.19 -> 0
C48: TOTAL | G48: =SUM(G46:G47) -> 398650 | I48: =SUM(I46:I47) -> 398650 | K48: =SUM(K46:K47) -> 398650 | M48: =SUM(M46:M47) -> 0
H56: Constructora MM

Sheet 9
B3: ESTADO DE PAGO Nº 1
M5: =+RESUMEN!D19 -> CORREDORA LUZ MARIA CORREA
B6: OBRA | C6: =+RESUMEN!C9 -> REMODELACION BAÑOS SHC LA CALERA
B7: UBICACIÓN | C7: =+RESUMEN!C10 -> MALL OPEN PLAZA LA CALERA | M7: Estado de pago
B8: CONTRATISTA | C8: =+RESUMEN!B20 -> DPTO 752 CONDOMINIO RAVELLO | M8: =+RESUMEN!I15 -> EEPP#06
B9: DIRECCION
B10: R.U.T. | C10: =+RESUMEN!C20 -> 11.520.369-K
B11: OC
B13: Monto Contratado a la Fecha | E13: =G43 -> 1230000 | L13: FECHA | M13: =+RESUMEN!I17 -> 45947
G15: TOTAL | H15: Avance Acumulado | J15: Avance E.P. ANTERIOR | L15: Presente
B16: ITEM | C16: DETALLE PARTIDAS | G16: CONTRATO | H16: a la Fecha | L16: Estado de Pago
H17: % | I17: Monto $ | J17: % | K17: Monto $ | L17: % | M17: Monto $
D18: UN | E18: CANT | F18: PU
B19: 1 | C19: ESPEJOS | D19: UNI | E19: 2 | F19: 100000 | G19: =+F19*E19 -> 200000 | H19: 1 | I19: =H19*G19 -> 200000 | J19: 1 | K19: =J19*G19 -> 200000 | L19: =H19-J19 -> 0 | M19: =L19*G19 -> 0
C20: MARCO DE PUERTA | D20: UNI | E20: 2 | F20: 325000 | G20: =+F20*E20 -> 650000 | H20: 1 | I20: =H20*G20 -> 650000 | J20: 1 | K20: =J20*G20 -> 650000 | L20: =H20-J20 -> 0 | M20: =L20*G20 -> 0
C21: VIDRIO VENTANA | D21: UNI | E21: 2 | F21: 15000 | G21: =+F21*E21 -> 30000 | H21: 1 | I21: =H21*G21 -> 30000 | J21: 1 | K21: =J21*G21 -> 30000 | L21: =H21-J21 -> 0 | M21: =L21*G21 -> 0
C22: TRASLADOS | D22: UNI | E22: 2 | F22: 175000 | G22: =+F22*E22 -> 350000 | H22: 1 | I22: =H22*G22 -> 350000 | J22: 1 | K22: =J22*G22 -> 350000 | L22: =H22-J22 -> 0 | M22: =L22*G22 -> 0
C43: SUB TOTAL | G43: =SUM(G18:G42) -> 1230000 | I43: =SUM(I18:I42) -> 1230000 | K43: =SUM(K18:K42) -> 1230000 | M43: =SUM(M18:M42) -> 0
C44: Retención | I44: =I43*F44 -> 0 | K44: =K43*F44 -> 0 | M44: =M43*F44 -> 0
C45: PAGO RETENCIONES | G45: 0 | H45: 0 | I45: =H45*G45 -> 0 | J45: 0 | K45: =G45*J45 -> 0 | L45: =H45-J45 -> 0 | M45: =L45*G45 -> 0
C46: NETO | G46: =G43-G44+G45 -> 1230000 | H46: ru | I46: =+I43-I44 -> 1230000 | K46: =+K43-K44 -> 1230000 | M46: =+M43-M44 -> 0
C47: 19% VALOR IVA | G47: =G46*19% -> 233700 | I47: =I46*19% -> 233700 | K47: =K46*19% -> 233700 | M47: =+M46*0.19 -> 0
C48: TOTAL | G48: =SUM(G46:G47) -> 1463700 | I48: =SUM(I46:I47) -> 1463700 | K48: =SUM(K46:K47) -> 1463700 | M48: =SUM(M46:M47) -> 0
H56: Constructora MM
